xudo/__init__.py
xudo/cli.py
xudo/commands/__init__.py
xudo/commands/base.py
xudo/commands/build.py
xudo/commands/clean.py
xudo/commands/dbpw.py
xudo/commands/jooq.py
xudo/commands/logs.py
xudo/commands/prune.py
xudo/commands/pull.py
xudo/commands/test.py
xudo/commands/up.py
xudo/commands/watch.py
xudo-1.1.1.dist-info/METADATA
xudo-1.1.1.dist-info/RECORD
xudo-1.1.1.dist-info/WHEEL
xudo-1.1.1.dist-info/entry_points.txt
xudo-1.1.1.dist-info/top_level.txt
